cbint/__init__.py
cbint/version.py
cbint/utils/__init__.py
cbint/utils/bridge.py
cbint/utils/cbserver.py
cbint/utils/daemon.py
cbint/utils/feed.py
cbint/utils/filesystem.py
cbint/utils/flaskfeed.py
cbint/utils/json.py
cbint/utils/tls.py
cbint/utils/detonation/__init__.py
cbint/utils/detonation/binary_analysis.py
cbint/utils/detonation/binary_queue.py
cbint/utils/templates/__init__.py
cbint/utils/templates/__init__.pyc
cbint-0.9.3.dist-info/LICENSE
cbint-0.9.3.dist-info/METADATA
cbint-0.9.3.dist-info/WHEEL
cbint-0.9.3.dist-info/top_level.txt
cbint-0.9.3.dist-info/RECORD
