Metadata-Version: 2.1
Name: cbint
Version: 0.9.3
Summary: Carbon Black Integration Library
Home-page: https://developer.carbonblack.com/
Author: Carbon Black
Author-email: dev-support@carbonblack.com
License: MIT
Platform: any
Classifier: Environment :: Web Environment
Classifier: Intended Audience :: Developers
Classifier: Operating System :: OS Independent
Classifier: Programming Language :: Python
Classifier: Topic :: Software Development :: Libraries :: Python Modules
Requires-Dist: flask
Requires-Dist: python-dateutil
Requires-Dist: netifaces
Requires-Dist: cbapi (>=1.3.4)
Requires-Dist: cbfeeds (==0.8.0)
Requires-Dist: requests
